{
  "lang": "ru",
  "entropy": 0.0,
  "mean_word_length": 0.0,
  "phoneme_counts": {
    "lʲ": 413244,
    "pʲ": 78306,
    "vʲ": 161356,
    "i": 1373052,
    "k": 520652,
    "j": 230830,
    "a": 1734692,
    "p": 427874,
    "l": 332814,
    "s": 867396,
    "b": 221730,
    "e": 1582762,
    "o": 1962242,
    "ɡ": 299392,
    "r": 885290,
    "v": 643658,
    "ɨ": 350696,
    "mʲ": 170652,
    "ɕː": 62842,
    "m": 401468,
    "u": 559818,
    "z": 257808,
    "x": 172570,
    "bʲ": 61282,
    "ʂ": 115654,
    "zʲ": 32566,
    "sʲ": 212528,
    "kʲ": 92144,
    "fʲ": 22270,
    "f": 33080,
    "xʲ": 6740,
    "tɕ": 222,
    "t": 571888,
    "n": 597405,
    "d": 181030,
    "tʲ": 168094,
    "dʲ": 83771,
    "nʲ": 8270,
    "ts": 5894
  },
  "observed_phonemes_count": 32,
  "total_phonemes_in_vocab": 0
}